nemoblock/__init__.py
nemoblock/_version.py
nemoblock/blocks.py
nemoblock/cylinder.py
nemoblock/experimental.py
nemoblock-1.0.4.dist-info/LICENSE
nemoblock-1.0.4.dist-info/METADATA
nemoblock-1.0.4.dist-info/WHEEL
nemoblock-1.0.4.dist-info/top_level.txt
nemoblock-1.0.4.dist-info/RECORD
