Metadata-Version: 2.1
Name: nemoblock
Version: 1.0.4
Summary: Utilities to generate blockMeshDicts for OpenFOAM.
Home-page: https://github.com/nemocrys/nemoblock
Author: Arved Enders-Seidlitz
Author-email: arved.enders-seidlitz@ikz-berlin.de
Classifier: Programming Language :: Python :: 3
Classifier: License :: OSI Approved :: GNU General Public License v3 or later (GPLv3+)
Classifier: Operating System :: OS Independent
Requires-Python: >=3.7
License-File: LICENSE
Requires-Dist: matplotlib
Requires-Dist: numpy
Requires-Dist: scipy
